zipmanip-0.1.0a2.dist-info/METADATA
zipmanip-0.1.0a2.dist-info/WHEEL
zipmanip-0.1.0a2.dist-info/entry_points.txt
zipmanip-0.1.0a2.dist-info/licenses/LICENSE
zipmanip.py
zipmanip-0.1.0a2.dist-info/RECORD
