Metadata-Version: 2.1
Name: zipmanip
Version: 0.1.0a2
Summary: Rewrite zip files, modifying compression type and parameters.
Author-Email: Jeff Dairiki <dairiki@dairiki.org>
License: MIT
Classifier: Development Status :: 4 - Beta
Classifier: Environment :: Console
Classifier: Intended Audience :: Developers
Classifier: Intended Audience :: End Users/Desktop
Classifier: License :: OSI Approved :: MIT License
Classifier: Programming Language :: Python :: 3
Classifier: Topic :: File Formats
Classifier: Topic :: Software Development :: Version Control :: Git
Classifier: Topic :: Utilities
Classifier: Typing :: Typed
Project-URL: Homepage, https://github.com/dairiki/zipmanip
Requires-Python: >=3.9
